decoda/__init__.py
decoda/exceptions.py
decoda/main.py
decoda/spec_loader.py
decoda/transport.py
decoda/well_known.py
decoda/sae_spec_converter/__init__.py
decoda/sae_spec_converter/correct_spec.py
decoda/sae_spec_converter/create_j1939db_json.py
decoda/sae_spec_converter/enrich_spec.py
decoda/sae_spec_converter/json_from_da.py
decoda/sae_spec_converter/json_from_isobus_xlsx.py
decoda/sae_spec_converter/make_extract.py
decoda/sae_spec_converter/remove_bad_items.py
decoda-0.2.7.dist-info/LICENSE
decoda-0.2.7.dist-info/METADATA
decoda-0.2.7.dist-info/WHEEL
decoda-0.2.7.dist-info/entry_points.txt
decoda-0.2.7.dist-info/top_level.txt
decoda-0.2.7.dist-info/RECORD
