Metadata-Version: 2.1
Name: decoda
Version: 0.2.7
Summary: Decoder for J1939
Home-page: https://www.decoda.cc/
Author: Andrew Dodd
Author-email: andrew.john.dodd@gmail.com
Maintainer: Andrew Dodd
Maintainer-email: andrew.john.dodd@gmail.com
License: MIT
Project-URL: Documentation, https://www.decoda.cc/
Project-URL: Source Code, https://github.com/andrewdodd/decoda
Keywords: j1939
Classifier: Development Status :: 3 - Alpha
Classifier: Intended Audience :: Developers
Classifier: Natural Language :: English
Classifier: License :: OSI Approved :: MIT License
Classifier: Operating System :: OS Independent
Classifier: Programming Language :: Python
Classifier: Programming Language :: Python :: 3
Classifier: Programming Language :: Python :: 3.6
Classifier: Programming Language :: Python :: 3.7
Classifier: Programming Language :: Python :: 3.8
Classifier: Programming Language :: Python :: 3.9
Classifier: Programming Language :: Python :: 3.10
Classifier: Topic :: Software Development :: Libraries :: Python Modules
Requires-Python: >=3.6
License-File: LICENSE
Requires-Dist: attrs
Provides-Extra: sae_spec_converter
Requires-Dist: pretty-j1939; extra == "sae-spec-converter"
Requires-Dist: xlrd2; extra == "sae-spec-converter"
Requires-Dist: pandas; extra == "sae-spec-converter"
Requires-Dist: openpyxl; extra == "sae-spec-converter"
